allak/__init__.py
allak/py.typed
allak/cli/__init__.py
allak/cli/click_types.py
allak/cli/main.py
allak/mac/__init__.py
allak/mac/eui_64.py
allak/mac/mac.py
allak-1.0.2.dist-info/LICENSE
allak-1.0.2.dist-info/METADATA
allak-1.0.2.dist-info/WHEEL
allak-1.0.2.dist-info/entry_points.txt
allak-1.0.2.dist-info/top_level.txt
allak-1.0.2.dist-info/RECORD
