Metadata-Version: 2.1
Name: allak
Version: 1.0.2
Summary: A CLI tool to produce an IPv6 address with the host portion being a modified EUI-64
Home-page: https://github.com/ttl256/allak
Author: Dmitrii Litovchenko
License: MIT
Keywords: ipv6,eui64
Platform: unix
Platform: linux
Platform: osx
Classifier: Programming Language :: Python :: 3 :: Only
Classifier: Programming Language :: Python :: 3.11
Classifier: Programming Language :: Python :: 3.12
Requires-Python: >=3.11
License-File: LICENSE
Requires-Dist: click >=8
Provides-Extra: testing
Requires-Dist: black >=23 ; extra == 'testing'
Requires-Dist: flake8 >=7 ; extra == 'testing'
Requires-Dist: mypy >=1.8 ; extra == 'testing'
Requires-Dist: pytest >=7.4 ; extra == 'testing'
Requires-Dist: pytest-cov >=4.1 ; extra == 'testing'
Requires-Dist: tox >=4 ; extra == 'testing'
